README.md
setup.py
long_image/__init__.py
long_image/image.py
long_image.egg-info/PKG-INFO
long_image.egg-info/SOURCES.txt
long_image.egg-info/dependency_links.txt
long_image.egg-info/top_level.txt