Metadata-Version: 1.1
Name: long-image
Version: 1.0.2
Summary: 添加图片数据流base64编码转本地图片
Home-page: https://gitee.com/zhenzi0322_admin/long_image
Author: zhenzi
Author-email: 82131529@qq.com
License: UNKNOWN
Platform: UNKNOWN
Classifier: Programming Language :: Python :: 3.7
Classifier: Operating System :: MacOS :: MacOS X
Classifier: Operating System :: POSIX :: Linux
